gc_metasploit/__init__.py
gc_metasploit/server.py
gc_metasploit-1.6.4.dist-info/METADATA
gc_metasploit-1.6.4.dist-info/WHEEL
gc_metasploit-1.6.4.dist-info/entry_points.txt
gc_metasploit-1.6.4.dist-info/licenses/LICENSE
gc_metasploit-1.6.4.dist-info/RECORD
