Metadata-Version: 2.4
Name: gc-metasploit
Version: 1.6.4
Summary: Metasploit MCP Server for AI assistants to interact with Metasploit Framework
Project-URL: Homepage, https://github.com/GH05TCREW/MetasploitMCP
Author: GhostCrew
License: Apache-2.0
License-File: LICENSE
Requires-Python: >=3.10
Requires-Dist: fastapi>=0.95.0
Requires-Dist: mcp>=1.2.0
Requires-Dist: pymetasploit3>=1.0.3
Requires-Dist: starlette>=0.26.1
Requires-Dist: uvicorn>=0.21.1
